{
  "required": true,
  "package": "net.ragdot.gestaltresonance.mixin",
  "compatibilityLevel": "JAVA_21",
  "mixins": ["BlockCollisionMixin", "EntityMixin", "ServerPlayerMixin", "PlayerMainHandMixin", "PlayerHasCorrectToolMixin"],
  "client": ["LivingEntitySwingMixin", "LivingEntityRendererTranslucencyMixin", "LivingEntityRendererSkipGearMixin", "PlayerRendererHandTranslucencyMixin", "ItemInHandRendererSkipItemMixin"],
  "injectors": {
    "defaultRequire": 1
  },
  "overwrites": {
    "requireAnnotations": true
  }
}